kohaku-board-ui/node_modules/katex/src/fonts/generate_fonts.py
kohaku-board-ui/node_modules/katex/src/metrics/extract_tfms.py
kohaku-board-ui/node_modules/katex/src/metrics/extract_ttfs.py
kohaku-board-ui/node_modules/katex/src/metrics/format_json.py
kohaku-board-ui/node_modules/katex/src/metrics/parse_tfm.py
kohakuboard/__init__.py
kohakuboard/cli.py
kohakuboard/config.py
kohakuboard/logger.py
kohakuboard/main.py
kohakuboard/api/__init__.py
kohakuboard/api/boards.py
kohakuboard/api/projects.py
kohakuboard/api/runs.py
kohakuboard/api/system.py
kohakuboard/client/__init__.py
kohakuboard/client/board.py
kohakuboard/client/capture.py
kohakuboard/client/sync_client.py
kohakuboard/client/sync_worker.py
kohakuboard/client/writer.py
kohakuboard/client/types/__init__.py
kohakuboard/client/types/histogram.py
kohakuboard/client/types/kernel_density.py
kohakuboard/client/types/media.py
kohakuboard/client/types/media_handler.py
kohakuboard/client/types/table.py
kohakuboard/client/types/tensor.py
kohakuboard/client/utils/__init__.py
kohakuboard/client/utils/media_hash.py
kohakuboard/data/__init__.py
kohakuboard/data/friendly_words/__init__.py
kohakuboard/data/friendly_words/objects.txt
kohakuboard/data/friendly_words/predicates.txt
kohakuboard/inspector/__init__.py
kohakuboard/inspector/app.py
kohakuboard/inspector/services/__init__.py
kohakuboard/inspector/services/data_service.py
kohakuboard/inspector/services/deletion_service.py
kohakuboard/inspector/services/export_service.py
kohakuboard/inspector/utils/__init__.py
kohakuboard/inspector/views/__init__.py
kohakuboard/inspector/views/board_content.py
kohakuboard/inspector/views/board_selector.py
kohakuboard/inspector/views/export_view.py
kohakuboard/inspector/views/histograms_view.py
kohakuboard/inspector/views/media_view.py
kohakuboard/inspector/views/metrics_view.py
kohakuboard/inspector/views/plots_view.py
kohakuboard/inspector/views/sql_view.py
kohakuboard/inspector/widgets/__init__.py
kohakuboard-0.0.1.dist-info/licenses/LICENSE
kohakuboard-0.0.1.dist-info/METADATA
kohakuboard-0.0.1.dist-info/WHEEL
kohakuboard-0.0.1.dist-info/entry_points.txt
kohakuboard-0.0.1.dist-info/top_level.txt
kohakuboard-0.0.1.dist-info/RECORD
