Metadata-Version: 2.4
Name: kohakuboard
Version: 0.0.1
Summary: High efficiency Local/self-hosted ML Experiment Tracking System
Author-email: "Shih-Ying Yeh(KohakuBlueLeaf)" <apolloyeh0123@gmail.com>
License: Apache-2.0
Project-URL: Homepage, https://github.com/KohakuBlueleaf/KohakuBoard
Requires-Python: >=3.10
License-File: LICENSE
Requires-Dist: aiofiles
Requires-Dist: aiohttp
Requires-Dist: bcrypt
Requires-Dist: boto3
Requires-Dist: cachetools
Requires-Dist: click>=8.0
Requires-Dist: click-completion
Requires-Dist: cryptography>=46.0
Requires-Dist: duckdb
Requires-Dist: fastapi
Requires-Dist: fsspec
Requires-Dist: httpx
Requires-Dist: kohakuvault
Requires-Dist: numpy
Requires-Dist: orjson
Requires-Dist: pandas
Requires-Dist: peewee
Requires-Dist: psycopg2-binary
Requires-Dist: pydantic[email]
Requires-Dist: python-multipart
Requires-Dist: pytz
Requires-Dist: pyyaml
Requires-Dist: questionary
Requires-Dist: requests
Requires-Dist: rich
Requires-Dist: toml
Requires-Dist: tqdm
Requires-Dist: uvicorn
Requires-Dist: pillow
Provides-Extra: inspector
Requires-Dist: customtkinter>=5.2.2; extra == "inspector"
Requires-Dist: matplotlib>=3.5.0; extra == "inspector"
Dynamic: license-file
